README.md
cdflow.1
cdflow.py
setup.py
cdflow.egg-info/PKG-INFO
cdflow.egg-info/SOURCES.txt
cdflow.egg-info/dependency_links.txt
cdflow.egg-info/entry_points.txt
cdflow.egg-info/requires.txt
cdflow.egg-info/top_level.txt
test/test_config.py
test/test_docker.py
test/test_fetch_release.py
test/test_integration.py
test/test_release_process.py