Metadata-Version: 2.1
Name: cdflow
Version: 205
Summary: Deployment tooling for continuous delivery
Home-page: https://mergermarket.github.io/cdflow
Author: Acuris
Author-email: platform@acuris.com
License: UNKNOWN
Keywords: continuous delivery terraform
Platform: UNKNOWN
Classifier: License :: OSI Approved :: MIT License
